blackduck/Authentication.py
blackduck/Client.py
blackduck/ClientCore.py
blackduck/Components.py
blackduck/Core.py
blackduck/CustomFields.py
blackduck/Exceptions.py
blackduck/ExtendedClient.py
blackduck/HubRestApi.py
blackduck/Jobs.py
blackduck/Ldap.py
blackduck/Licences.py
blackduck/Policy.py
blackduck/Projects.py
blackduck/Reporting.py
blackduck/Roles.py
blackduck/Scans.py
blackduck/Snippet.py
blackduck/System.py
blackduck/UserGroup.py
blackduck/Users.py
blackduck/Utils.py
blackduck/Versions.py
blackduck/Vulnerabilities.py
blackduck/__init__.py
blackduck/__version__.py
blackduck/constants.py
blackduck-1.1.0.dist-info/LICENSE
blackduck-1.1.0.dist-info/METADATA
blackduck-1.1.0.dist-info/WHEEL
blackduck-1.1.0.dist-info/top_level.txt
blackduck-1.1.0.dist-info/RECORD
