Metadata-Version: 2.1
Name: blackduck
Version: 1.1.0
Summary: Package for using the Synopsys Black Duck Hub REST API.
Home-page: https://github.com/blackducksoftware/hub-rest-api-python
Author: Glenn Snyder
Author-email: gsnyder@synopsys.com
License: Apache
Keywords: api
Platform: UNKNOWN
Classifier: License :: OSI Approved :: Apache Software License
Classifier: Programming Language :: Python
Classifier: Programming Language :: Python :: 3
Classifier: Programming Language :: Python :: 3.6
Classifier: Programming Language :: Python :: Implementation :: CPython
Classifier: Programming Language :: Python :: Implementation :: PyPy
Requires-Python: >=3.6.0
License-File: LICENSE
